slurpy/__init__.py
slurpy/v0040/__init__.py
slurpy/v0040/api/__init__.py
slurpy/v0040/api/slurm_api.py
slurpy/v0040/api/slurmdb_api.py
slurpy/v0040/api_client.py
slurpy/v0040/api_response.py
slurpy/v0040/asyncio/__init__.py
slurpy/v0040/asyncio/api/__init__.py
slurpy/v0040/asyncio/api/slurm_api.py
slurpy/v0040/asyncio/api/slurmdb_api.py
slurpy/v0040/asyncio/api_client.py
slurpy/v0040/asyncio/api_response.py
slurpy/v0040/asyncio/configuration.py
slurpy/v0040/asyncio/docs/SlurmApi.md
slurpy/v0040/asyncio/docs/SlurmdbApi.md
slurpy/v0040/asyncio/exceptions.py
slurpy/v0040/asyncio/models/__init__.py
slurpy/v0040/asyncio/models/account.py
slurpy/v0040/asyncio/models/account_short.py
slurpy/v0040/asyncio/models/accounting.py
slurpy/v0040/asyncio/models/accounts_add_cond.py
slurpy/v0040/asyncio/models/acct_gather_energy.py
slurpy/v0040/asyncio/models/assoc.py
slurpy/v0040/asyncio/models/assoc_rec_set.py
slurpy/v0040/asyncio/models/assoc_shares_obj_wrap.py
slurpy/v0040/asyncio/models/assoc_short.py
slurpy/v0040/asyncio/models/bf_exit_fields.py
slurpy/v0040/asyncio/models/cluster_rec.py
slurpy/v0040/asyncio/models/controller_ping.py
slurpy/v0040/asyncio/models/coord.py
slurpy/v0040/asyncio/models/cron_entry.py
slurpy/v0040/asyncio/models/float64_no_val.py
slurpy/v0040/asyncio/models/instance.py
slurpy/v0040/asyncio/models/job.py
slurpy/v0040/asyncio/models/job_array_response_msg_entry.py
slurpy/v0040/asyncio/models/job_desc_msg.py
slurpy/v0040/asyncio/models/job_info.py
slurpy/v0040/asyncio/models/job_res.py
slurpy/v0040/asyncio/models/job_submit_req.py
slurpy/v0040/asyncio/models/job_submit_response_msg.py
slurpy/v0040/asyncio/models/kill_jobs_msg.py
slurpy/v0040/asyncio/models/kill_jobs_resp_job.py
slurpy/v0040/asyncio/models/license.py
slurpy/v0040/asyncio/models/node.py
slurpy/v0040/asyncio/models/open_api_accounts_add_cond_resp.py
slurpy/v0040/asyncio/models/open_api_accounts_add_cond_resp_str.py
slurpy/v0040/asyncio/models/open_api_accounts_removed_resp.py
ebi_slurpy-0.1.1.dist-info/LICENSE
ebi_slurpy-0.1.1.dist-info/METADATA
ebi_slurpy-0.1.1.dist-info/WHEEL
ebi_slurpy-0.1.1.dist-info/RECORD
