Metadata-Version: 2.3
Name: ebi-slurpy
Version: 0.1.1
Summary: Python client for the Slurm REST API
License: Apache-2.0
Keywords: slurm,hpc,rest-api,job-scheduler
Author: Sandy Rogers
Author-email: sandyr@ebi.ac.uk
Requires-Python: >=3.11,<4.0
Classifier: Development Status :: 3 - Alpha
Classifier: Intended Audience :: Developers
Classifier: License :: OSI Approved :: Apache Software License
Classifier: Programming Language :: Python :: 3
Classifier: Programming Language :: Python :: 3.11
Classifier: Programming Language :: Python :: 3.12
Classifier: Programming Language :: Python :: 3.13
Classifier: Topic :: System :: Distributed Computing
Requires-Dist: aiohttp (>=3.8.4)
Requires-Dist: aiohttp-retry (>=2.8.3)
Requires-Dist: pydantic (>=2.9.2,<3.0.0)
Requires-Dist: python-dateutil (>=2.8.2)
Requires-Dist: typing-extensions (>=4.7.1)
Project-URL: Homepage, https://github.com/EBI-Metagenomics/slurpy
Project-URL: Repository, https://github.com/EBI-Metagenomics/slurpy
